deepcompressor/__init__.py
deepcompressor/app/__init__.py
deepcompressor/app/diffusion/__init__.py
deepcompressor/app/diffusion/cache/__init__.py
deepcompressor/app/diffusion/cache/config.py
deepcompressor/app/diffusion/config.py
deepcompressor/app/diffusion/dataset/__init__.py
deepcompressor/app/diffusion/dataset/base.py
deepcompressor/app/diffusion/dataset/calib.py
deepcompressor/app/diffusion/dataset/collect/calib.py
deepcompressor/app/diffusion/dataset/collect/utils.py
deepcompressor/app/diffusion/dataset/data/COCO/COCO.py
deepcompressor/app/diffusion/dataset/data/COCO/__init__.py
deepcompressor/app/diffusion/dataset/data/DCI/DCI.py
deepcompressor/app/diffusion/dataset/data/DCI/__init__.py
deepcompressor/app/diffusion/dataset/data/MJHQ/MJHQ.py
deepcompressor/app/diffusion/dataset/data/MJHQ/__init__.py
deepcompressor/app/diffusion/dataset/data/__init__.py
deepcompressor/app/diffusion/dataset/data/dump.py
deepcompressor/app/diffusion/eval/__init__.py
deepcompressor/app/diffusion/eval/config.py
deepcompressor/app/diffusion/eval/metrics/__init__.py
deepcompressor/app/diffusion/eval/metrics/fid.py
deepcompressor/app/diffusion/eval/metrics/image_reward.py
deepcompressor/app/diffusion/eval/metrics/multimodal.py
deepcompressor/app/diffusion/eval/metrics/run.py
deepcompressor/app/diffusion/eval/metrics/similarity.py
deepcompressor/app/diffusion/nn/__init__.py
deepcompressor/app/diffusion/nn/attention.py
deepcompressor/app/diffusion/nn/patch.py
deepcompressor/app/diffusion/nn/struct.py
deepcompressor/app/diffusion/pipeline/__init__.py
deepcompressor/app/diffusion/pipeline/config.py
deepcompressor/app/diffusion/ptq.py
deepcompressor/app/diffusion/quant/__init__.py
deepcompressor/app/diffusion/quant/activation.py
deepcompressor/app/diffusion/quant/config.py
deepcompressor/app/diffusion/quant/quantizer/__init__.py
deepcompressor/app/diffusion/quant/quantizer/config.py
deepcompressor/app/diffusion/quant/quantizer/quantizer.py
deepcompressor/app/diffusion/quant/rotate.py
deepcompressor_toolkit-0.1.0.dist-info/LICENSE
deepcompressor_toolkit-0.1.0.dist-info/METADATA
deepcompressor_toolkit-0.1.0.dist-info/WHEEL
deepcompressor_toolkit-0.1.0.dist-info/RECORD
