Metadata-Version: 2.3
Name: deepcompressor-toolkit
Version: 0.1.0
Summary: This package is model compression toolkit for large language models and diffusion models.
License: Apache-2.0
Author: Yujun Lin
Requires-Python: >=3.10,<4.0
Classifier: License :: OSI Approved :: Apache Software License
Classifier: Programming Language :: Python :: 3
Classifier: Programming Language :: Python :: 3.10
Classifier: Programming Language :: Python :: 3.11
Classifier: Programming Language :: Python :: 3.12
Classifier: Programming Language :: Python :: 3.13
Requires-Dist: accelerate (>=0.26.0)
Requires-Dist: bitsandbytes (>=0.42.0)
Requires-Dist: bs4 (>=0.0.2)
Requires-Dist: cd-fvd (>=0.1.1)
Requires-Dist: clean-fid (>=0.1.35)
Requires-Dist: clip (>=0.2.0)
Requires-Dist: datasets (>=2.16.0)
Requires-Dist: diffusers (>=0.32.0)
Requires-Dist: dominate (>=2.9.1)
Requires-Dist: einops (>=0.8.0)
Requires-Dist: ftfy (>=6.2.0)
Requires-Dist: fuzzywuzzy (>=0.18.0)
Requires-Dist: jieba (>=0.42.1)
Requires-Dist: lm_eval (>=0.4.2)
Requires-Dist: ninja (>=1.11.1)
Requires-Dist: omniconfig (>=0.1.10)
Requires-Dist: opencv-python (>=4.10.0)
Requires-Dist: protobuf (>=5.26.0)
Requires-Dist: pyav (>=13.0.0)
Requires-Dist: python-Levenshtein (>=0.26.1)
Requires-Dist: rotary-embedding-torch (>=0.6.4)
Requires-Dist: rouge (>=1.0.1)
Requires-Dist: sentencepiece (>=0.1.99)
Requires-Dist: timm (>=1.0.7)
Requires-Dist: torch (>=2.5.0)
Requires-Dist: torchmetrics (>=1.4.0)
Requires-Dist: torchvision (>=0.18.1)
Requires-Dist: tqdm (>=4.66.0)
Requires-Dist: transformers (>=4.46.0)
Requires-Dist: xformers (>=0.0.26)
